topsis/__init__.py
topsis/__main__.py
topsis_102003553-1.1.0.dist-info/LICENSE.txt
topsis_102003553-1.1.0.dist-info/METADATA
topsis_102003553-1.1.0.dist-info/WHEEL
topsis_102003553-1.1.0.dist-info/entry_points.txt
topsis_102003553-1.1.0.dist-info/top_level.txt
topsis_102003553-1.1.0.dist-info/RECORD
