Metadata-Version: 2.1
Name: topsis-102003553
Version: 1.1.0
Summary: A Python package to find TOPSIS for multi-criteria decision analysis method
Home-page: https://github.com/Sarvagy-Jain/topsis_python_package
Author: Sarvagy Jain
Author-email: sarvagyjain @gmail.com
License: MIT
Keywords: UCS538,TIET
Classifier: Development Status :: 3 - Alpha
Classifier: Intended Audience :: Developers
Classifier: Operating System :: Microsoft :: Windows :: Windows 10
Classifier: License :: OSI Approved :: MIT License
Classifier: Programming Language :: Python :: 3
License-File: LICENSE.txt
Requires-Dist: pandas
Requires-Dist: tabulate
